bladerunner/__init__.py
bladerunner/base.py
bladerunner/cmdline.py
bladerunner/formatting.py
bladerunner/interactive.py
bladerunner/networking.py
bladerunner/progressbar.py
bladerunner-4.1.9.dist-info/DESCRIPTION.rst
bladerunner-4.1.9.dist-info/METADATA
bladerunner-4.1.9.dist-info/RECORD
bladerunner-4.1.9.dist-info/WHEEL
bladerunner-4.1.9.dist-info/entry_points.txt
bladerunner-4.1.9.dist-info/metadata.json
bladerunner-4.1.9.dist-info/top_level.txt
