Metadata-Version: 2.0
Name: bladerunner
Version: 4.1.9
Summary: Execution of commands on hosts
Home-page: https://github.com/a-tal/bladerunner
Author: Adam Talsma
Author-email: adam@talsma.ca
License: GPLv2
Download-URL: https://github.com/a-tal/bladerunner
Platform: UNKNOWN
Classifier: Development Status :: 5 - Production/Stable
Classifier: Environment :: Console
Classifier: Intended Audience :: System Administrators
Classifier: License :: OSI Approved :: GNU General Public License v2 (GPLv2)
Classifier: Operating System :: POSIX :: Linux
Classifier: Topic :: System :: Clustering
Classifier: Topic :: System :: Systems Administration
Classifier: Programming Language :: Python
Classifier: Programming Language :: Python :: 2
Classifier: Programming Language :: Python :: 2.7
Classifier: Programming Language :: Python :: 3
Classifier: Programming Language :: Python :: 3.3
Classifier: Programming Language :: Python :: 3.4
Requires-Dist: pexpect (>=3.3)
Requires-Dist: six (>=1.9.0)
